easy_inspect-0.1.0.dist-info/METADATA
easy_inspect-0.1.0.dist-info/WHEEL
easy_inspect-0.1.0.dist-info/entry_points.txt
easy_inspect/__init__.py
easy_inspect/loading.py
easy_inspect/plotting.py
easy_inspect/question.py
easy_inspect/runner.py
easy_inspect/scorer/__init__.py
easy_inspect/scorer/dummy.py
easy_inspect/scorer/model_graded_rating.py
easy_inspect-0.1.0.dist-info/RECORD
